<?xml version="1.0" encoding="UTF-8"?>
<hash>
  <tree>
    <region>Pacific</region>
    <description>Kwomtari: Laycock 1975</description>
    <root>
      <start-date nil="true"></start-date>
      <other-codes></other-codes>
      <created-at type="datetime">2013-05-17T10:43:13-04:00</created-at>
      <confidence>y</confidence>
      <tree-val>Kwomtari: Laycock 1975</tree-val>
      <pub-comments>&quot;Lexically, the languages show a certain amount of influence from the Trans-New Guinea Phylum languages; the question of whether the Kwomtari Phylum may in fact be a sub-phylum of the Trans-New Guinea Phylum remains open&quot; (Laycock 1975: 854).  Population: 3,246?</pub-comments>
      <node-status-id nil="true"></node-status-id>
      <updated-at type="datetime">2013-05-17T10:43:14-04:00</updated-at>
      <pri-name>Kwomtari Phylum</pri-name>
      <node-type>Subgroup</node-type>
      <is-default type="boolean">false</is-default>
      <deleted-at nil="true"></deleted-at>
      <sureness type="integer">0</sureness>
      <id type="integer">870024</id>
      <creator-id type="integer">10740</creator-id>
      <created-by>joe_leif</created-by>
      <updater-id type="integer">10740</updater-id>
      <geography nil="true"></geography>
      <updated-by>joe_leif</updated-by>
      <node-type-id type="integer">10000</node-type-id>
      <alt-names></alt-names>
      <tree-id type="integer">21825</tree-id>
      <codes>kwba</codes>
      <status nil="true"></status>
      <publications>Laycock, Donald C. 1975.  Papuan languages and the New Guinea linguistic scene: New Guinea area languages and language study, vol. 1, 853-854. Canberra: Dept. of Linguistics, Research School of Pacific Studies, Australian National University. </publications>
      <end-date nil="true"></end-date>
      <children type="array">
        <child>
          <start-date nil="true"></start-date>
          <other-codes></other-codes>
          <created-at type="datetime">2013-05-17T10:43:14-04:00</created-at>
          <confidence>y</confidence>
          <tree-val>Kwomtari: Laycock 1975</tree-val>
          <pub-comments>Population: 100?</pub-comments>
          <node-status-id nil="true"></node-status-id>
          <updated-at type="datetime">2013-05-17T10:43:14-04:00</updated-at>
          <pri-name>Pyu Family</pri-name>
          <node-type>Subgroup</node-type>
          <is-default type="boolean">false</is-default>
          <deleted-at nil="true"></deleted-at>
          <sureness type="integer">0</sureness>
          <id type="integer">870031</id>
          <creator-id type="integer">10740</creator-id>
          <created-by>joe_leif</created-by>
          <updater-id type="integer">10740</updater-id>
          <geography nil="true"></geography>
          <updated-by>joe_leif</updated-by>
          <node-type-id type="integer">10000</node-type-id>
          <alt-names></alt-names>
          <tree-id type="integer">21825</tree-id>
          <codes>pyuu</codes>
          <status nil="true"></status>
          <publications>Laycock, Donald C. 1975.  Papuan languages and the New Guinea linguistic scene: New Guinea area languages and language study, vol. 1, 853-854. Canberra: Dept. of Linguistics, Research School of Pacific Studies, Australian National University. </publications>
          <end-date nil="true"></end-date>
          <children type="array">
            <child>
              <start-date nil="true"></start-date>
              <other-codes></other-codes>
              <created-at type="datetime">2013-05-17T10:43:14-04:00</created-at>
              <confidence>y</confidence>
              <tree-val>Kwomtari: Laycock 1975</tree-val>
              <pub-comments>Population: 100?</pub-comments>
              <node-status-id nil="true"></node-status-id>
              <updated-at type="datetime">2013-05-17T10:43:14-04:00</updated-at>
              <pri-name>Pyu</pri-name>
              <node-type>Language</node-type>
              <is-default type="boolean">false</is-default>
              <deleted-at nil="true"></deleted-at>
              <sureness type="integer">0</sureness>
              <id type="integer">870032</id>
              <creator-id type="integer">10740</creator-id>
              <created-by>joe_leif</created-by>
              <updater-id type="integer">10740</updater-id>
              <geography>over the border of Irian Jaya (West Papua Province, Indonesia) on the Blake River, found at Buriap Village, on the Upper Sepik River</geography>
              <updated-by>joe_leif</updated-by>
              <node-type-id type="integer">10001</node-type-id>
              <alt-names></alt-names>
              <tree-id type="integer">21825</tree-id>
              <codes>pby</codes>
              <status nil="true"></status>
              <publications>Laycock, Donald C. 1975.  Papuan languages and the New Guinea linguistic scene: New Guinea area languages and language study, vol. 1, 853-854. Canberra: Dept. of Linguistics, Research School of Pacific Studies, Australian National University. </publications>
              <end-date nil="true"></end-date>
              <children type="array"/>
            </child>
          </children>
        </child>
        <child>
          <start-date nil="true"></start-date>
          <other-codes></other-codes>
          <created-at type="datetime">2013-05-17T10:43:14-04:00</created-at>
          <confidence>y</confidence>
          <tree-val>Kwomtari: Laycock 1975</tree-val>
          <pub-comments>Population: 2,421</pub-comments>
          <node-status-id nil="true"></node-status-id>
          <updated-at type="datetime">2013-05-17T10:43:14-04:00</updated-at>
          <pri-name>Kwomtari Family</pri-name>
          <node-type>Subgroup</node-type>
          <is-default type="boolean">false</is-default>
          <deleted-at nil="true"></deleted-at>
          <sureness type="integer">0</sureness>
          <id type="integer">870025</id>
          <creator-id type="integer">10740</creator-id>
          <created-by>joe_leif</created-by>
          <updater-id type="integer">10740</updater-id>
          <geography nil="true"></geography>
          <updated-by>joe_leif</updated-by>
          <node-type-id type="integer">10000</node-type-id>
          <alt-names></alt-names>
          <tree-id type="integer">21825</tree-id>
          <codes>kwom</codes>
          <status nil="true"></status>
          <publications>Laycock, Donald C. 1975.  Papuan languages and the New Guinea linguistic scene: New Guinea area languages and language study, vol. 1, 853-854. Canberra: Dept. of Linguistics, Research School of Pacific Studies, Australian National University. </publications>
          <end-date nil="true"></end-date>
          <children type="array">
            <child>
              <start-date nil="true"></start-date>
              <other-codes></other-codes>
              <created-at type="datetime">2013-05-17T10:43:14-04:00</created-at>
              <confidence>y</confidence>
              <tree-val>Kwomtari: Laycock 1975</tree-val>
              <pub-comments>Population: 824</pub-comments>
              <node-status-id nil="true"></node-status-id>
              <updated-at type="datetime">2013-05-17T10:43:14-04:00</updated-at>
              <pri-name>Kwomtari</pri-name>
              <node-type>Language</node-type>
              <is-default type="boolean">false</is-default>
              <deleted-at nil="true"></deleted-at>
              <sureness type="integer">0</sureness>
              <id type="integer">870026</id>
              <creator-id type="integer">10740</creator-id>
              <created-by>joe_leif</created-by>
              <updater-id type="integer">10740</updater-id>
              <geography nil="true"></geography>
              <updated-by>joe_leif</updated-by>
              <node-type-id type="integer">10001</node-type-id>
              <alt-names></alt-names>
              <tree-id type="integer">21825</tree-id>
              <codes>kwo</codes>
              <status nil="true"></status>
              <publications>Laycock, Donald C. 1975.  Papuan languages and the New Guinea linguistic scene: New Guinea area languages and language study, vol. 1, 853-854. Canberra: Dept. of Linguistics, Research School of Pacific Studies, Australian National University. </publications>
              <end-date nil="true"></end-date>
              <children type="array"/>
            </child>
            <child>
              <start-date nil="true"></start-date>
              <other-codes></other-codes>
              <created-at type="datetime">2013-05-17T10:43:14-04:00</created-at>
              <confidence>y</confidence>
              <tree-val>Kwomtari: Laycock 1975</tree-val>
              <pub-comments>Population: 1,597</pub-comments>
              <node-status-id nil="true"></node-status-id>
              <updated-at type="datetime">2013-05-17T10:43:14-04:00</updated-at>
              <pri-name>Fas</pri-name>
              <node-type>Language</node-type>
              <is-default type="boolean">false</is-default>
              <deleted-at nil="true"></deleted-at>
              <sureness type="integer">0</sureness>
              <id type="integer">870027</id>
              <creator-id type="integer">10740</creator-id>
              <created-by>joe_leif</created-by>
              <updater-id type="integer">10740</updater-id>
              <geography>extending out of the Amanab subdistrict into the Aitape, Lumi, and Vanimo subdistricts</geography>
              <updated-by>joe_leif</updated-by>
              <node-type-id type="integer">10001</node-type-id>
              <alt-names></alt-names>
              <tree-id type="integer">21825</tree-id>
              <codes>fqs</codes>
              <status nil="true"></status>
              <publications>Laycock, Donald C. 1975.  Papuan languages and the New Guinea linguistic scene: New Guinea area languages and language study, vol. 1, 853-854. Canberra: Dept. of Linguistics, Research School of Pacific Studies, Australian National University. </publications>
              <end-date nil="true"></end-date>
              <children type="array"/>
            </child>
          </children>
        </child>
        <child>
          <start-date nil="true"></start-date>
          <other-codes></other-codes>
          <created-at type="datetime">2013-05-17T10:43:14-04:00</created-at>
          <confidence>y</confidence>
          <tree-val>Kwomtari: Laycock 1975</tree-val>
          <pub-comments>Population: 725</pub-comments>
          <node-status-id nil="true"></node-status-id>
          <updated-at type="datetime">2013-05-17T10:43:14-04:00</updated-at>
          <pri-name>Baibai Family</pri-name>
          <node-type>Subgroup</node-type>
          <is-default type="boolean">false</is-default>
          <deleted-at nil="true"></deleted-at>
          <sureness type="integer">0</sureness>
          <id type="integer">870028</id>
          <creator-id type="integer">10740</creator-id>
          <created-by>joe_leif</created-by>
          <updater-id type="integer">10740</updater-id>
          <geography nil="true"></geography>
          <updated-by>joe_leif</updated-by>
          <node-type-id type="integer">10000</node-type-id>
          <alt-names></alt-names>
          <tree-id type="integer">21825</tree-id>
          <codes>baib</codes>
          <status nil="true"></status>
          <publications>Laycock, Donald C. 1975.  Papuan languages and the New Guinea linguistic scene: New Guinea area languages and language study, vol. 1, 853-854. Canberra: Dept. of Linguistics, Research School of Pacific Studies, Australian National University. </publications>
          <end-date nil="true"></end-date>
          <children type="array">
            <child>
              <start-date nil="true"></start-date>
              <other-codes></other-codes>
              <created-at type="datetime">2013-05-17T10:43:14-04:00</created-at>
              <confidence>y</confidence>
              <tree-val>Kwomtari: Laycock 1975</tree-val>
              <pub-comments>Population: 271</pub-comments>
              <node-status-id nil="true"></node-status-id>
              <updated-at type="datetime">2013-05-17T10:43:14-04:00</updated-at>
              <pri-name>Baibai</pri-name>
              <node-type>Language</node-type>
              <is-default type="boolean">false</is-default>
              <deleted-at nil="true"></deleted-at>
              <sureness type="integer">0</sureness>
              <id type="integer">870029</id>
              <creator-id type="integer">10740</creator-id>
              <created-by>joe_leif</created-by>
              <updater-id type="integer">10740</updater-id>
              <geography nil="true"></geography>
              <updated-by>joe_leif</updated-by>
              <node-type-id type="integer">10001</node-type-id>
              <alt-names></alt-names>
              <tree-id type="integer">21825</tree-id>
              <codes>bbf</codes>
              <status nil="true"></status>
              <publications>Laycock, Donald C. 1975.  Papuan languages and the New Guinea linguistic scene: New Guinea area languages and language study, vol. 1, 853-854. Canberra: Dept. of Linguistics, Research School of Pacific Studies, Australian National University. </publications>
              <end-date nil="true"></end-date>
              <children type="array"/>
            </child>
            <child>
              <start-date nil="true"></start-date>
              <other-codes></other-codes>
              <created-at type="datetime">2013-05-17T10:43:14-04:00</created-at>
              <confidence>y</confidence>
              <tree-val>Kwomtari: Laycock 1975</tree-val>
              <pub-comments>Population: 454</pub-comments>
              <node-status-id nil="true"></node-status-id>
              <updated-at type="datetime">2013-05-17T10:43:14-04:00</updated-at>
              <pri-name>Biaka</pri-name>
              <node-type>Language</node-type>
              <is-default type="boolean">false</is-default>
              <deleted-at nil="true"></deleted-at>
              <sureness type="integer">0</sureness>
              <id type="integer">870030</id>
              <creator-id type="integer">10740</creator-id>
              <created-by>joe_leif</created-by>
              <updater-id type="integer">10740</updater-id>
              <geography nil="true"></geography>
              <updated-by>joe_leif</updated-by>
              <node-type-id type="integer">10001</node-type-id>
              <alt-names></alt-names>
              <tree-id type="integer">21825</tree-id>
              <codes>bio</codes>
              <status nil="true"></status>
              <publications>Laycock, Donald C. 1975.  Papuan languages and the New Guinea linguistic scene: New Guinea area languages and language study, vol. 1, 853-854. Canberra: Dept. of Linguistics, Research School of Pacific Studies, Australian National University. </publications>
              <end-date nil="true"></end-date>
              <children type="array"/>
            </child>
          </children>
        </child>
      </children>
    </root>
  </tree>
</hash>
