<?xml version="1.0" encoding="UTF-8"?>
<hash>
  <tree>
    <region>Africa</region>
    <root>
      <start-date nil="true"></start-date>
      <pub-comments>&#8220;This subgrouping is based on both lexicostatistics evidence and on the evidence of unifiable innovation found among subsets of the languages&#8221; (Black 1974:8).</pub-comments>
      <geography nil="true"></geography>
      <updater-id type="integer">10640</updater-id>
      <id type="integer">957205</id>
      <end-date nil="true"></end-date>
      <creator-id type="integer">10640</creator-id>
      <codes>cush</codes>
      <is-default type="integer">0</is-default>
      <created-by>emily</created-by>
      <confidence>y</confidence>
      <updated-by>emily</updated-by>
      <tree-val>Lowland East Cushitic, a subtree of Afroasiatic: Black 1974</tree-val>
      <publications>Black, Paul. 1974. Lowland East Cushitic: Subgrouping and Reconstruction. </publications>
      <node-status-id nil="true"></node-status-id>
      <alt-names></alt-names>
      <node-type>Subgroup</node-type>
      <status nil="true"></status>
      <other-codes></other-codes>
      <tree-id type="integer">24398</tree-id>
      <sureness type="integer">0</sureness>
      <node-type-id type="integer">10000</node-type-id>
      <created-at type="datetime">2013-07-25T14:21:15-04:00</created-at>
      <updated-at type="datetime">2013-07-25T14:21:15-04:00</updated-at>
      <pri-name>Cushitic</pri-name>
      <deleted-at nil="true"></deleted-at>
      <children type="array">
        <child>
          <start-date nil="true"></start-date>
          <pub-comments></pub-comments>
          <geography nil="true"></geography>
          <updater-id type="integer">10640</updater-id>
          <id type="integer">957208</id>
          <end-date nil="true"></end-date>
          <creator-id type="integer">10640</creator-id>
          <codes>llnd</codes>
          <is-default type="integer">0</is-default>
          <created-by>emily</created-by>
          <confidence>y</confidence>
          <updated-by>emily</updated-by>
          <tree-val>Lowland East Cushitic, a subtree of Afroasiatic: Black 1974</tree-val>
          <publications>Black, Paul. 1974. Lowland East Cushitic: Subgrouping and Reconstruction. </publications>
          <node-status-id nil="true"></node-status-id>
          <alt-names></alt-names>
          <node-type>Subgroup</node-type>
          <status nil="true"></status>
          <other-codes></other-codes>
          <tree-id type="integer">24398</tree-id>
          <sureness type="integer">0</sureness>
          <node-type-id type="integer">10000</node-type-id>
          <created-at type="datetime">2013-07-25T14:21:15-04:00</created-at>
          <updated-at type="datetime">2013-07-25T14:21:15-04:00</updated-at>
          <pri-name>Lowland East Cushitic</pri-name>
          <deleted-at nil="true"></deleted-at>
          <children type="array">
            <child>
              <start-date nil="true"></start-date>
              <pub-comments></pub-comments>
              <geography nil="true"></geography>
              <updater-id type="integer">10640</updater-id>
              <id type="integer">957219</id>
              <end-date nil="true"></end-date>
              <creator-id type="integer">10640</creator-id>
              <codes>slec</codes>
              <is-default type="integer">0</is-default>
              <created-by>emily</created-by>
              <confidence>y</confidence>
              <updated-by>emily</updated-by>
              <tree-val>Lowland East Cushitic, a subtree of Afroasiatic: Black 1974</tree-val>
              <publications>Black, Paul. 1974. Lowland East Cushitic: Subgrouping and Reconstruction. </publications>
              <node-status-id nil="true"></node-status-id>
              <alt-names></alt-names>
              <node-type>Subgroup</node-type>
              <status nil="true"></status>
              <other-codes></other-codes>
              <tree-id type="integer">24398</tree-id>
              <sureness type="integer">0</sureness>
              <node-type-id type="integer">10000</node-type-id>
              <created-at type="datetime">2013-07-25T14:21:17-04:00</created-at>
              <updated-at type="datetime">2013-07-25T14:21:17-04:00</updated-at>
              <pri-name>Southern Lowland East Cushitic</pri-name>
              <deleted-at nil="true"></deleted-at>
              <children type="array">
                <child>
                  <start-date nil="true"></start-date>
                  <pub-comments></pub-comments>
                  <geography nil="true"></geography>
                  <updater-id type="integer">10640</updater-id>
                  <id type="integer">957237</id>
                  <end-date nil="true"></end-date>
                  <creator-id type="integer">10640</creator-id>
                  <codes>orom</codes>
                  <is-default type="integer">0</is-default>
                  <created-by>emily</created-by>
                  <confidence>y</confidence>
                  <updated-by>emily</updated-by>
                  <tree-val>Lowland East Cushitic, a subtree of Afroasiatic: Black 1974</tree-val>
                  <publications>Black, Paul. 1974. Lowland East Cushitic: Subgrouping and Reconstruction. </publications>
                  <node-status-id nil="true"></node-status-id>
                  <alt-names></alt-names>
                  <node-type>Subgroup</node-type>
                  <status nil="true"></status>
                  <other-codes></other-codes>
                  <tree-id type="integer">24398</tree-id>
                  <sureness type="integer">0</sureness>
                  <node-type-id type="integer">10000</node-type-id>
                  <created-at type="datetime">2013-07-25T14:21:18-04:00</created-at>
                  <updated-at type="datetime">2013-07-25T14:21:18-04:00</updated-at>
                  <pri-name>Oromoid</pri-name>
                  <deleted-at nil="true"></deleted-at>
                  <children type="array">
                    <child>
                      <start-date nil="true"></start-date>
                      <pub-comments>&#8220;Konsoid is a chain of dialects spoken in southwestern Ethiopia by some hundred thousand people&#8221; (Black 1974:12).</pub-comments>
                      <geography>Southwestern Ethiopia.</geography>
                      <updater-id type="integer">10640</updater-id>
                      <id type="integer">957247</id>
                      <end-date nil="true"></end-date>
                      <creator-id type="integer">10640</creator-id>
                      <codes>kong</codes>
                      <is-default type="integer">0</is-default>
                      <created-by>emily</created-by>
                      <confidence>y</confidence>
                      <updated-by>emily</updated-by>
                      <tree-val>Lowland East Cushitic, a subtree of Afroasiatic: Black 1974</tree-val>
                      <publications>Black, Paul. 1974. Lowland East Cushitic: Subgrouping and Reconstruction. </publications>
                      <node-status-id nil="true"></node-status-id>
                      <alt-names></alt-names>
                      <node-type>Subgroup</node-type>
                      <status nil="true"></status>
                      <other-codes></other-codes>
                      <tree-id type="integer">24398</tree-id>
                      <sureness type="integer">0</sureness>
                      <node-type-id type="integer">10000</node-type-id>
                      <created-at type="datetime">2013-07-25T14:21:19-04:00</created-at>
                      <updated-at type="datetime">2013-07-25T14:21:19-04:00</updated-at>
                      <pri-name>Konsoid</pri-name>
                      <deleted-at nil="true"></deleted-at>
                      <children type="array">
                        <child>
                          <start-date nil="true"></start-date>
                          <pub-comments></pub-comments>
                          <geography nil="true"></geography>
                          <updater-id type="integer">10640</updater-id>
                          <id type="integer">957248</id>
                          <end-date nil="true"></end-date>
                          <creator-id type="integer">10640</creator-id>
                          <codes>kxc</codes>
                          <is-default type="integer">0</is-default>
                          <created-by>emily</created-by>
                          <confidence>y</confidence>
                          <updated-by>emily</updated-by>
                          <tree-val>Lowland East Cushitic, a subtree of Afroasiatic: Black 1974</tree-val>
                          <publications>Black, Paul. 1974. Lowland East Cushitic: Subgrouping and Reconstruction. </publications>
                          <node-status-id nil="true"></node-status-id>
                          <alt-names></alt-names>
                          <node-type>Language</node-type>
                          <status nil="true"></status>
                          <other-codes></other-codes>
                          <tree-id type="integer">24398</tree-id>
                          <sureness type="integer">0</sureness>
                          <node-type-id type="integer">10001</node-type-id>
                          <created-at type="datetime">2013-07-25T14:21:19-04:00</created-at>
                          <updated-at type="datetime">2013-07-25T14:21:19-04:00</updated-at>
                          <pri-name>Konso</pri-name>
                          <deleted-at nil="true"></deleted-at>
                          <children type="array"/>
                        </child>
                        <child>
                          <start-date nil="true"></start-date>
                          <pub-comments></pub-comments>
                          <geography nil="true"></geography>
                          <updater-id type="integer">10640</updater-id>
                          <id type="integer">957252</id>
                          <end-date nil="true"></end-date>
                          <creator-id type="integer">10640</creator-id>
                          <codes>dox</codes>
                          <is-default type="integer">0</is-default>
                          <created-by>emily</created-by>
                          <confidence>y</confidence>
                          <updated-by>emily</updated-by>
                          <tree-val>Lowland East Cushitic, a subtree of Afroasiatic: Black 1974</tree-val>
                          <publications>Black, Paul. 1974. Lowland East Cushitic: Subgrouping and Reconstruction. </publications>
                          <node-status-id nil="true"></node-status-id>
                          <alt-names></alt-names>
                          <node-type>Language</node-type>
                          <status nil="true"></status>
                          <other-codes></other-codes>
                          <tree-id type="integer">24398</tree-id>
                          <sureness type="integer">0</sureness>
                          <node-type-id type="integer">10001</node-type-id>
                          <created-at type="datetime">2013-07-25T14:21:19-04:00</created-at>
                          <updated-at type="datetime">2013-07-25T14:21:19-04:00</updated-at>
                          <pri-name>Mashile</pri-name>
                          <deleted-at nil="true"></deleted-at>
                          <children type="array"/>
                        </child>
                        <child>
                          <start-date nil="true"></start-date>
                          <pub-comments></pub-comments>
                          <geography nil="true"></geography>
                          <updater-id type="integer">10640</updater-id>
                          <id type="integer">957251</id>
                          <end-date nil="true"></end-date>
                          <creator-id type="integer">10640</creator-id>
                          <codes>kxc</codes>
                          <is-default type="integer">0</is-default>
                          <created-by>emily</created-by>
                          <confidence nil="true"></confidence>
                          <updated-by>emily</updated-by>
                          <tree-val>Lowland East Cushitic, a subtree of Afroasiatic: Black 1974</tree-val>
                          <publications>Black, Paul. 1974. Lowland East Cushitic: Subgrouping and Reconstruction. </publications>
                          <node-status-id nil="true"></node-status-id>
                          <alt-names></alt-names>
                          <node-type>Language</node-type>
                          <status nil="true"></status>
                          <other-codes></other-codes>
                          <tree-id type="integer">24398</tree-id>
                          <sureness nil="true"></sureness>
                          <node-type-id type="integer">10001</node-type-id>
                          <created-at type="datetime">2013-07-25T14:21:19-04:00</created-at>
                          <updated-at type="datetime">2013-07-25T14:21:19-04:00</updated-at>
                          <pri-name>Gato</pri-name>
                          <deleted-at nil="true"></deleted-at>
                          <children type="array"/>
                        </child>
                        <child>
                          <start-date nil="true"></start-date>
                          <pub-comments></pub-comments>
                          <geography nil="true"></geography>
                          <updater-id type="integer">10640</updater-id>
                          <id type="integer">957249</id>
                          <end-date nil="true"></end-date>
                          <creator-id type="integer">10640</creator-id>
                          <codes>dox</codes>
                          <is-default type="integer">0</is-default>
                          <created-by>emily</created-by>
                          <confidence nil="true"></confidence>
                          <updated-by>emily</updated-by>
                          <tree-val>Lowland East Cushitic, a subtree of Afroasiatic: Black 1974</tree-val>
                          <publications>Black, Paul. 1974. Lowland East Cushitic: Subgrouping and Reconstruction. </publications>
                          <node-status-id nil="true"></node-status-id>
                          <alt-names></alt-names>
                          <node-type>Language</node-type>
                          <status nil="true"></status>
                          <other-codes></other-codes>
                          <tree-id type="integer">24398</tree-id>
                          <sureness nil="true"></sureness>
                          <node-type-id type="integer">10001</node-type-id>
                          <created-at type="datetime">2013-07-25T14:21:19-04:00</created-at>
                          <updated-at type="datetime">2013-07-25T14:21:19-04:00</updated-at>
                          <pri-name>Busssa</pri-name>
                          <deleted-at nil="true"></deleted-at>
                          <children type="array"/>
                        </child>
                        <child>
                          <start-date nil="true"></start-date>
                          <pub-comments></pub-comments>
                          <geography nil="true"></geography>
                          <updater-id type="integer">10640</updater-id>
                          <id type="integer">957253</id>
                          <end-date nil="true"></end-date>
                          <creator-id type="integer">10640</creator-id>
                          <codes>gdl</codes>
                          <is-default type="integer">0</is-default>
                          <created-by>emily</created-by>
                          <confidence>y</confidence>
                          <updated-by>emily</updated-by>
                          <tree-val>Lowland East Cushitic, a subtree of Afroasiatic: Black 1974</tree-val>
                          <publications>Black, Paul. 1974. Lowland East Cushitic: Subgrouping and Reconstruction. </publications>
                          <node-status-id nil="true"></node-status-id>
                          <alt-names></alt-names>
                          <node-type>Language</node-type>
                          <status nil="true"></status>
                          <other-codes></other-codes>
                          <tree-id type="integer">24398</tree-id>
                          <sureness type="integer">0</sureness>
                          <node-type-id type="integer">10001</node-type-id>
                          <created-at type="datetime">2013-07-25T14:21:19-04:00</created-at>
                          <updated-at type="datetime">2013-07-25T14:21:20-04:00</updated-at>
                          <pri-name>Gidole</pri-name>
                          <deleted-at nil="true"></deleted-at>
                          <children type="array"/>
                        </child>
                        <child>
                          <start-date nil="true"></start-date>
                          <pub-comments></pub-comments>
                          <geography nil="true"></geography>
                          <updater-id type="integer">10640</updater-id>
                          <id type="integer">957250</id>
                          <end-date nil="true"></end-date>
                          <creator-id type="integer">10640</creator-id>
                          <codes>1z8</codes>
                          <is-default type="integer">0</is-default>
                          <created-by>emily</created-by>
                          <confidence nil="true"></confidence>
                          <updated-by>emily</updated-by>
                          <tree-val>Lowland East Cushitic, a subtree of Afroasiatic: Black 1974</tree-val>
                          <publications>Black, Paul. 1974. Lowland East Cushitic: Subgrouping and Reconstruction. </publications>
                          <node-status-id nil="true"></node-status-id>
                          <alt-names></alt-names>
                          <node-type>Language</node-type>
                          <status nil="true"></status>
                          <other-codes></other-codes>
                          <tree-id type="integer">24398</tree-id>
                          <sureness nil="true"></sureness>
                          <node-type-id type="integer">10001</node-type-id>
                          <created-at type="datetime">2013-07-25T14:21:19-04:00</created-at>
                          <updated-at type="datetime">2013-07-25T14:21:19-04:00</updated-at>
                          <pri-name>Turo</pri-name>
                          <deleted-at nil="true"></deleted-at>
                          <children type="array"/>
                        </child>
                      </children>
                    </child>
                    <child>
                      <start-date nil="true"></start-date>
                      <pub-comments>&#8220;Galla is spoken by perhaps as many as seven million [people]...it serves as a lingua franca in many areas in Southern Ethiopia&#8221; (Black 1974:11).</pub-comments>
                      <geography>Western, central, and southern Ethiopia, and by additional speakers in northern Kenya.</geography>
                      <updater-id type="integer">10640</updater-id>
                      <id type="integer">957238</id>
                      <end-date nil="true"></end-date>
                      <creator-id type="integer">10640</creator-id>
                      <codes>gax, gaz</codes>
                      <is-default type="integer">0</is-default>
                      <created-by>emily</created-by>
                      <confidence>y</confidence>
                      <updated-by>emily</updated-by>
                      <tree-val>Lowland East Cushitic, a subtree of Afroasiatic: Black 1974</tree-val>
                      <publications>Black, Paul. 1974. Lowland East Cushitic: Subgrouping and Reconstruction. </publications>
                      <node-status-id nil="true"></node-status-id>
                      <alt-names></alt-names>
                      <node-type>Language</node-type>
                      <status nil="true"></status>
                      <other-codes></other-codes>
                      <tree-id type="integer">24398</tree-id>
                      <sureness type="integer">0</sureness>
                      <node-type-id type="integer">10001</node-type-id>
                      <created-at type="datetime">2013-07-25T14:21:18-04:00</created-at>
                      <updated-at type="datetime">2013-07-25T14:21:18-04:00</updated-at>
                      <pri-name>Galla</pri-name>
                      <deleted-at nil="true"></deleted-at>
                      <children type="array">
                        <child>
                          <start-date nil="true"></start-date>
                          <pub-comments></pub-comments>
                          <geography nil="true"></geography>
                          <updater-id type="integer">10640</updater-id>
                          <id type="integer">957245</id>
                          <end-date nil="true"></end-date>
                          <creator-id type="integer">10640</creator-id>
                          <codes>gaz-mec</codes>
                          <is-default type="integer">0</is-default>
                          <created-by>emily</created-by>
                          <confidence nil="true"></confidence>
                          <updated-by>emily</updated-by>
                          <tree-val>Lowland East Cushitic, a subtree of Afroasiatic: Black 1974</tree-val>
                          <publications>Black, Paul. 1974. Lowland East Cushitic: Subgrouping and Reconstruction. </publications>
                          <node-status-id nil="true"></node-status-id>
                          <alt-names></alt-names>
                          <node-type>Dialect</node-type>
                          <status nil="true"></status>
                          <other-codes></other-codes>
                          <tree-id type="integer">24398</tree-id>
                          <sureness nil="true"></sureness>
                          <node-type-id type="integer">10003</node-type-id>
                          <created-at type="datetime">2013-07-25T14:21:19-04:00</created-at>
                          <updated-at type="datetime">2013-07-25T14:21:19-04:00</updated-at>
                          <pri-name>Wollega</pri-name>
                          <deleted-at nil="true"></deleted-at>
                          <children type="array"/>
                        </child>
                        <child>
                          <start-date nil="true"></start-date>
                          <pub-comments></pub-comments>
                          <geography nil="true"></geography>
                          <updater-id type="integer">10640</updater-id>
                          <id type="integer">957243</id>
                          <end-date nil="true"></end-date>
                          <creator-id type="integer">10640</creator-id>
                          <codes>gax-ars</codes>
                          <is-default type="integer">0</is-default>
                          <created-by>emily</created-by>
                          <confidence nil="true"></confidence>
                          <updated-by>emily</updated-by>
                          <tree-val>Lowland East Cushitic, a subtree of Afroasiatic: Black 1974</tree-val>
                          <publications>Black, Paul. 1974. Lowland East Cushitic: Subgrouping and Reconstruction. </publications>
                          <node-status-id nil="true"></node-status-id>
                          <alt-names></alt-names>
                          <node-type>Dialect</node-type>
                          <status nil="true"></status>
                          <other-codes></other-codes>
                          <tree-id type="integer">24398</tree-id>
                          <sureness nil="true"></sureness>
                          <node-type-id type="integer">10003</node-type-id>
                          <created-at type="datetime">2013-07-25T14:21:19-04:00</created-at>
                          <updated-at type="datetime">2013-07-25T14:21:19-04:00</updated-at>
                          <pri-name>Arussi</pri-name>
                          <deleted-at nil="true"></deleted-at>
                          <children type="array"/>
                        </child>
                        <child>
                          <start-date nil="true"></start-date>
                          <pub-comments></pub-comments>
                          <geography nil="true"></geography>
                          <updater-id type="integer">10640</updater-id>
                          <id type="integer">957244</id>
                          <end-date nil="true"></end-date>
                          <creator-id type="integer">10640</creator-id>
                          <codes>gaz-tul</codes>
                          <is-default type="integer">0</is-default>
                          <created-by>emily</created-by>
                          <confidence nil="true"></confidence>
                          <updated-by>emily</updated-by>
                          <tree-val>Lowland East Cushitic, a subtree of Afroasiatic: Black 1974</tree-val>
                          <publications>Black, Paul. 1974. Lowland East Cushitic: Subgrouping and Reconstruction. </publications>
                          <node-status-id nil="true"></node-status-id>
                          <alt-names></alt-names>
                          <node-type>Dialect</node-type>
                          <status nil="true"></status>
                          <other-codes></other-codes>
                          <tree-id type="integer">24398</tree-id>
                          <sureness nil="true"></sureness>
                          <node-type-id type="integer">10003</node-type-id>
                          <created-at type="datetime">2013-07-25T14:21:19-04:00</created-at>
                          <updated-at type="datetime">2013-07-25T14:21:19-04:00</updated-at>
                          <pri-name>Shoa</pri-name>
                          <deleted-at nil="true"></deleted-at>
                          <children type="array"/>
                        </child>
                        <child>
                          <start-date nil="true"></start-date>
                          <pub-comments></pub-comments>
                          <geography nil="true"></geography>
                          <updater-id type="integer">10640</updater-id>
                          <id type="integer">957242</id>
                          <end-date nil="true"></end-date>
                          <creator-id type="integer">10640</creator-id>
                          <codes>gax-hae</codes>
                          <is-default type="integer">0</is-default>
                          <created-by>emily</created-by>
                          <confidence nil="true"></confidence>
                          <updated-by>emily</updated-by>
                          <tree-val>Lowland East Cushitic, a subtree of Afroasiatic: Black 1974</tree-val>
                          <publications>Black, Paul. 1974. Lowland East Cushitic: Subgrouping and Reconstruction. </publications>
                          <node-status-id nil="true"></node-status-id>
                          <alt-names></alt-names>
                          <node-type>Dialect</node-type>
                          <status nil="true"></status>
                          <other-codes></other-codes>
                          <tree-id type="integer">24398</tree-id>
                          <sureness nil="true"></sureness>
                          <node-type-id type="integer">10003</node-type-id>
                          <created-at type="datetime">2013-07-25T14:21:19-04:00</created-at>
                          <updated-at type="datetime">2013-07-25T14:21:19-04:00</updated-at>
                          <pri-name>Qottu</pri-name>
                          <deleted-at nil="true"></deleted-at>
                          <children type="array"/>
                        </child>
                        <child>
                          <start-date nil="true"></start-date>
                          <pub-comments></pub-comments>
                          <geography nil="true"></geography>
                          <updater-id type="integer">10640</updater-id>
                          <id type="integer">957239</id>
                          <end-date nil="true"></end-date>
                          <creator-id type="integer">10640</creator-id>
                          <codes>qsg</codes>
                          <is-default type="integer">0</is-default>
                          <created-by>emily</created-by>
                          <confidence nil="true"></confidence>
                          <updated-by>emily</updated-by>
                          <tree-val>Lowland East Cushitic, a subtree of Afroasiatic: Black 1974</tree-val>
                          <publications>Black, Paul. 1974. Lowland East Cushitic: Subgrouping and Reconstruction. </publications>
                          <node-status-id nil="true"></node-status-id>
                          <alt-names></alt-names>
                          <node-type>Dialect</node-type>
                          <status nil="true"></status>
                          <other-codes></other-codes>
                          <tree-id type="integer">24398</tree-id>
                          <sureness nil="true"></sureness>
                          <node-type-id type="integer">10003</node-type-id>
                          <created-at type="datetime">2013-07-25T14:21:18-04:00</created-at>
                          <updated-at type="datetime">2013-07-25T14:21:19-04:00</updated-at>
                          <pri-name>Bararetta</pri-name>
                          <deleted-at nil="true"></deleted-at>
                          <children type="array"/>
                        </child>
                        <child>
                          <start-date nil="true"></start-date>
                          <pub-comments></pub-comments>
                          <geography nil="true"></geography>
                          <updater-id type="integer">10640</updater-id>
                          <id type="integer">957240</id>
                          <end-date nil="true"></end-date>
                          <creator-id type="integer">10640</creator-id>
                          <codes>gax</codes>
                          <is-default type="integer">0</is-default>
                          <created-by>emily</created-by>
                          <confidence nil="true"></confidence>
                          <updated-by>emily</updated-by>
                          <tree-val>Lowland East Cushitic, a subtree of Afroasiatic: Black 1974</tree-val>
                          <publications>Black, Paul. 1974. Lowland East Cushitic: Subgrouping and Reconstruction. </publications>
                          <node-status-id nil="true"></node-status-id>
                          <alt-names></alt-names>
                          <node-type>Dialect</node-type>
                          <status nil="true"></status>
                          <other-codes></other-codes>
                          <tree-id type="integer">24398</tree-id>
                          <sureness nil="true"></sureness>
                          <node-type-id type="integer">10003</node-type-id>
                          <created-at type="datetime">2013-07-25T14:21:19-04:00</created-at>
                          <updated-at type="datetime">2013-07-25T14:21:19-04:00</updated-at>
                          <pri-name>Borana</pri-name>
                          <deleted-at nil="true"></deleted-at>
                          <children type="array"/>
                        </child>
                        <child>
                          <start-date nil="true"></start-date>
                          <pub-comments></pub-comments>
                          <geography nil="true"></geography>
                          <updater-id type="integer">10640</updater-id>
                          <id type="integer">957246</id>
                          <end-date nil="true"></end-date>
                          <creator-id type="integer">10640</creator-id>
                          <codes>gax-wol</codes>
                          <is-default type="integer">0</is-default>
                          <created-by>emily</created-by>
                          <confidence nil="true"></confidence>
                          <updated-by>emily</updated-by>
                          <tree-val>Lowland East Cushitic, a subtree of Afroasiatic: Black 1974</tree-val>
                          <publications>Black, Paul. 1974. Lowland East Cushitic: Subgrouping and Reconstruction. </publications>
                          <node-status-id nil="true"></node-status-id>
                          <alt-names></alt-names>
                          <node-type>Dialect</node-type>
                          <status nil="true"></status>
                          <other-codes></other-codes>
                          <tree-id type="integer">24398</tree-id>
                          <sureness nil="true"></sureness>
                          <node-type-id type="integer">10003</node-type-id>
                          <created-at type="datetime">2013-07-25T14:21:19-04:00</created-at>
                          <updated-at type="datetime">2013-07-25T14:21:19-04:00</updated-at>
                          <pri-name>Wolo Galla</pri-name>
                          <deleted-at nil="true"></deleted-at>
                          <children type="array"/>
                        </child>
                        <child>
                          <start-date nil="true"></start-date>
                          <pub-comments></pub-comments>
                          <geography nil="true"></geography>
                          <updater-id type="integer">10640</updater-id>
                          <id type="integer">957241</id>
                          <end-date nil="true"></end-date>
                          <creator-id type="integer">10640</creator-id>
                          <codes>gax-guj</codes>
                          <is-default type="integer">0</is-default>
                          <created-by>emily</created-by>
                          <confidence nil="true"></confidence>
                          <updated-by>emily</updated-by>
                          <tree-val>Lowland East Cushitic, a subtree of Afroasiatic: Black 1974</tree-val>
                          <publications>Black, Paul. 1974. Lowland East Cushitic: Subgrouping and Reconstruction. </publications>
                          <node-status-id nil="true"></node-status-id>
                          <alt-names></alt-names>
                          <node-type>Dialect</node-type>
                          <status nil="true"></status>
                          <other-codes></other-codes>
                          <tree-id type="integer">24398</tree-id>
                          <sureness nil="true"></sureness>
                          <node-type-id type="integer">10003</node-type-id>
                          <created-at type="datetime">2013-07-25T14:21:19-04:00</created-at>
                          <updated-at type="datetime">2013-07-25T14:21:19-04:00</updated-at>
                          <pri-name>Guji</pri-name>
                          <deleted-at nil="true"></deleted-at>
                          <children type="array"/>
                        </child>
                      </children>
                    </child>
                  </children>
                </child>
                <child>
                  <start-date nil="true"></start-date>
                  <pub-comments></pub-comments>
                  <geography nil="true"></geography>
                  <updater-id type="integer">10640</updater-id>
                  <id type="integer">957220</id>
                  <end-date nil="true"></end-date>
                  <creator-id type="integer">10640</creator-id>
                  <codes>soba</codes>
                  <is-default type="integer">0</is-default>
                  <created-by>emily</created-by>
                  <confidence>y</confidence>
                  <updated-by>emily</updated-by>
                  <tree-val>Lowland East Cushitic, a subtree of Afroasiatic: Black 1974</tree-val>
                  <publications>Black, Paul. 1974. Lowland East Cushitic: Subgrouping and Reconstruction. </publications>
                  <node-status-id nil="true"></node-status-id>
                  <alt-names></alt-names>
                  <node-type>Subgroup</node-type>
                  <status nil="true"></status>
                  <other-codes></other-codes>
                  <tree-id type="integer">24398</tree-id>
                  <sureness type="integer">0</sureness>
                  <node-type-id type="integer">10000</node-type-id>
                  <created-at type="datetime">2013-07-25T14:21:17-04:00</created-at>
                  <updated-at type="datetime">2013-07-25T14:21:17-04:00</updated-at>
                  <pri-name>Baiso-Somaloid</pri-name>
                  <deleted-at nil="true"></deleted-at>
                  <children type="array">
                    <child>
                      <start-date nil="true"></start-date>
                      <pub-comments></pub-comments>
                      <geography nil="true"></geography>
                      <updater-id type="integer">10640</updater-id>
                      <id type="integer">957222</id>
                      <end-date nil="true"></end-date>
                      <creator-id type="integer">10640</creator-id>
                      <codes>soma</codes>
                      <is-default type="integer">0</is-default>
                      <created-by>emily</created-by>
                      <confidence>y</confidence>
                      <updated-by>emily</updated-by>
                      <tree-val>Lowland East Cushitic, a subtree of Afroasiatic: Black 1974</tree-val>
                      <publications>Black, Paul. 1974. Lowland East Cushitic: Subgrouping and Reconstruction. </publications>
                      <node-status-id nil="true"></node-status-id>
                      <alt-names></alt-names>
                      <node-type>Subgroup</node-type>
                      <status nil="true"></status>
                      <other-codes></other-codes>
                      <tree-id type="integer">24398</tree-id>
                      <sureness type="integer">0</sureness>
                      <node-type-id type="integer">10000</node-type-id>
                      <created-at type="datetime">2013-07-25T14:21:17-04:00</created-at>
                      <updated-at type="datetime">2013-07-25T14:21:17-04:00</updated-at>
                      <pri-name>Somaloid</pri-name>
                      <deleted-at nil="true"></deleted-at>
                      <children type="array">
                        <child>
                          <start-date nil="true"></start-date>
                          <pub-comments>&#8220;Somali is spoken by severanl million people...it has become the official language of the country [Somalia], and has come to be the only Cushitic language to possess an officially recognized orthography&#8221; (Black 1974:11).</pub-comments>
                          <geography>The whole of Somalia plus adjacent areas of French Somaliland, kenya, and the Ogaden region of Ethiopia.</geography>
                          <updater-id type="integer">10640</updater-id>
                          <id type="integer">957223</id>
                          <end-date nil="true"></end-date>
                          <creator-id type="integer">10640</creator-id>
                          <codes>som</codes>
                          <is-default type="integer">0</is-default>
                          <created-by>emily</created-by>
                          <confidence>y</confidence>
                          <updated-by>emily</updated-by>
                          <tree-val>Lowland East Cushitic, a subtree of Afroasiatic: Black 1974</tree-val>
                          <publications>Black, Paul. 1974. Lowland East Cushitic: Subgrouping and Reconstruction. </publications>
                          <node-status-id nil="true"></node-status-id>
                          <alt-names></alt-names>
                          <node-type>Language</node-type>
                          <status nil="true"></status>
                          <other-codes></other-codes>
                          <tree-id type="integer">24398</tree-id>
                          <sureness type="integer">0</sureness>
                          <node-type-id type="integer">10001</node-type-id>
                          <created-at type="datetime">2013-07-25T14:21:17-04:00</created-at>
                          <updated-at type="datetime">2013-07-25T14:21:17-04:00</updated-at>
                          <pri-name>Somali</pri-name>
                          <deleted-at nil="true"></deleted-at>
                          <children type="array">
                            <child>
                              <start-date nil="true"></start-date>
                              <pub-comments></pub-comments>
                              <geography nil="true"></geography>
                              <updater-id type="integer">10640</updater-id>
                              <id type="integer">957227</id>
                              <end-date nil="true"></end-date>
                              <creator-id type="integer">10640</creator-id>
                              <codes>som</codes>
                              <is-default type="integer">0</is-default>
                              <created-by>emily</created-by>
                              <confidence nil="true"></confidence>
                              <updated-by>emily</updated-by>
                              <tree-val>Lowland East Cushitic, a subtree of Afroasiatic: Black 1974</tree-val>
                              <publications>Black, Paul. 1974. Lowland East Cushitic: Subgrouping and Reconstruction. </publications>
                              <node-status-id nil="true"></node-status-id>
                              <alt-names></alt-names>
                              <node-type>Dialect</node-type>
                              <status nil="true"></status>
                              <other-codes></other-codes>
                              <tree-id type="integer">24398</tree-id>
                              <sureness nil="true"></sureness>
                              <node-type-id type="integer">10003</node-type-id>
                              <created-at type="datetime">2013-07-25T14:21:17-04:00</created-at>
                              <updated-at type="datetime">2013-07-25T14:21:17-04:00</updated-at>
                              <pri-name>Darod</pri-name>
                              <deleted-at nil="true"></deleted-at>
                              <children type="array"/>
                            </child>
                            <child>
                              <start-date nil="true"></start-date>
                              <pub-comments></pub-comments>
                              <geography nil="true"></geography>
                              <updater-id type="integer">10640</updater-id>
                              <id type="integer">957228</id>
                              <end-date nil="true"></end-date>
                              <creator-id type="integer">10640</creator-id>
                              <codes>awn</codes>
                              <is-default type="integer">0</is-default>
                              <created-by>emily</created-by>
                              <confidence nil="true"></confidence>
                              <updated-by>emily</updated-by>
                              <tree-val>Lowland East Cushitic, a subtree of Afroasiatic: Black 1974</tree-val>
                              <publications>Black, Paul. 1974. Lowland East Cushitic: Subgrouping and Reconstruction. </publications>
                              <node-status-id nil="true"></node-status-id>
                              <alt-names></alt-names>
                              <node-type>Dialect</node-type>
                              <status nil="true"></status>
                              <other-codes></other-codes>
                              <tree-id type="integer">24398</tree-id>
                              <sureness nil="true"></sureness>
                              <node-type-id type="integer">10003</node-type-id>
                              <created-at type="datetime">2013-07-25T14:21:17-04:00</created-at>
                              <updated-at type="datetime">2013-07-25T14:21:18-04:00</updated-at>
                              <pri-name>Hawiya</pri-name>
                              <deleted-at nil="true"></deleted-at>
                              <children type="array"/>
                            </child>
                            <child>
                              <start-date nil="true"></start-date>
                              <pub-comments></pub-comments>
                              <geography nil="true"></geography>
                              <updater-id type="integer">10640</updater-id>
                              <id type="integer">957230</id>
                              <end-date nil="true"></end-date>
                              <creator-id type="integer">10640</creator-id>
                              <codes>ymm</codes>
                              <is-default type="integer">0</is-default>
                              <created-by>emily</created-by>
                              <confidence nil="true"></confidence>
                              <updated-by>emily</updated-by>
                              <tree-val>Lowland East Cushitic, a subtree of Afroasiatic: Black 1974</tree-val>
                              <publications>Black, Paul. 1974. Lowland East Cushitic: Subgrouping and Reconstruction. </publications>
                              <node-status-id nil="true"></node-status-id>
                              <alt-names></alt-names>
                              <node-type>Dialect</node-type>
                              <status nil="true"></status>
                              <other-codes></other-codes>
                              <tree-id type="integer">24398</tree-id>
                              <sureness nil="true"></sureness>
                              <node-type-id type="integer">10003</node-type-id>
                              <created-at type="datetime">2013-07-25T14:21:18-04:00</created-at>
                              <updated-at type="datetime">2013-07-25T14:21:18-04:00</updated-at>
                              <pri-name>Rahamreyn</pri-name>
                              <deleted-at nil="true"></deleted-at>
                              <children type="array"/>
                            </child>
                            <child>
                              <start-date nil="true"></start-date>
                              <pub-comments></pub-comments>
                              <geography nil="true"></geography>
                              <updater-id type="integer">10640</updater-id>
                              <id type="integer">957226</id>
                              <end-date nil="true"></end-date>
                              <creator-id type="integer">10640</creator-id>
                              <codes>som-gad</codes>
                              <is-default type="integer">0</is-default>
                              <created-by>emily</created-by>
                              <confidence nil="true"></confidence>
                              <updated-by>emily</updated-by>
                              <tree-val>Lowland East Cushitic, a subtree of Afroasiatic: Black 1974</tree-val>
                              <publications>Black, Paul. 1974. Lowland East Cushitic: Subgrouping and Reconstruction. </publications>
                              <node-status-id nil="true"></node-status-id>
                              <alt-names></alt-names>
                              <node-type>Dialect</node-type>
                              <status nil="true"></status>
                              <other-codes></other-codes>
                              <tree-id type="integer">24398</tree-id>
                              <sureness nil="true"></sureness>
                              <node-type-id type="integer">10003</node-type-id>
                              <created-at type="datetime">2013-07-25T14:21:17-04:00</created-at>
                              <updated-at type="datetime">2013-07-25T14:21:17-04:00</updated-at>
                              <pri-name>Gadabursi</pri-name>
                              <deleted-at nil="true"></deleted-at>
                              <children type="array"/>
                            </child>
                            <child>
                              <start-date nil="true"></start-date>
                              <pub-comments></pub-comments>
                              <geography nil="true"></geography>
                              <updater-id type="integer">10640</updater-id>
                              <id type="integer">957229</id>
                              <end-date nil="true"></end-date>
                              <creator-id type="integer">10640</creator-id>
                              <codes>som-ben</codes>
                              <is-default type="integer">0</is-default>
                              <created-by>emily</created-by>
                              <confidence nil="true"></confidence>
                              <updated-by>emily</updated-by>
                              <tree-val>Lowland East Cushitic, a subtree of Afroasiatic: Black 1974</tree-val>
                              <publications>Black, Paul. 1974. Lowland East Cushitic: Subgrouping and Reconstruction. </publications>
                              <node-status-id nil="true"></node-status-id>
                              <alt-names></alt-names>
                              <node-type>Dialect</node-type>
                              <status nil="true"></status>
                              <other-codes></other-codes>
                              <tree-id type="integer">24398</tree-id>
                              <sureness nil="true"></sureness>
                              <node-type-id type="integer">10003</node-type-id>
                              <created-at type="datetime">2013-07-25T14:21:18-04:00</created-at>
                              <updated-at type="datetime">2013-07-25T14:21:18-04:00</updated-at>
                              <pri-name>Benadir</pri-name>
                              <deleted-at nil="true"></deleted-at>
                              <children type="array"/>
                            </child>
                            <child>
                              <start-date nil="true"></start-date>
                              <pub-comments></pub-comments>
                              <geography nil="true"></geography>
                              <updater-id type="integer">10640</updater-id>
                              <id type="integer">957224</id>
                              <end-date nil="true"></end-date>
                              <creator-id type="integer">10640</creator-id>
                              <codes>som</codes>
                              <is-default type="integer">0</is-default>
                              <created-by>emily</created-by>
                              <confidence nil="true"></confidence>
                              <updated-by>emily</updated-by>
                              <tree-val>Lowland East Cushitic, a subtree of Afroasiatic: Black 1974</tree-val>
                              <publications>Black, Paul. 1974. Lowland East Cushitic: Subgrouping and Reconstruction. </publications>
                              <node-status-id nil="true"></node-status-id>
                              <alt-names></alt-names>
                              <node-type>Dialect</node-type>
                              <status nil="true"></status>
                              <other-codes></other-codes>
                              <tree-id type="integer">24398</tree-id>
                              <sureness nil="true"></sureness>
                              <node-type-id type="integer">10003</node-type-id>
                              <created-at type="datetime">2013-07-25T14:21:17-04:00</created-at>
                              <updated-at type="datetime">2013-07-25T14:21:17-04:00</updated-at>
                              <pri-name>Issaq</pri-name>
                              <deleted-at nil="true"></deleted-at>
                              <children type="array"/>
                            </child>
                            <child>
                              <start-date nil="true"></start-date>
                              <pub-comments></pub-comments>
                              <geography nil="true"></geography>
                              <updater-id type="integer">10640</updater-id>
                              <id type="integer">957225</id>
                              <end-date nil="true"></end-date>
                              <creator-id type="integer">10640</creator-id>
                              <codes>som</codes>
                              <is-default type="integer">0</is-default>
                              <created-by>emily</created-by>
                              <confidence nil="true"></confidence>
                              <updated-by>emily</updated-by>
                              <tree-val>Lowland East Cushitic, a subtree of Afroasiatic: Black 1974</tree-val>
                              <publications>Black, Paul. 1974. Lowland East Cushitic: Subgrouping and Reconstruction. </publications>
                              <node-status-id nil="true"></node-status-id>
                              <alt-names></alt-names>
                              <node-type>Dialect</node-type>
                              <status nil="true"></status>
                              <other-codes></other-codes>
                              <tree-id type="integer">24398</tree-id>
                              <sureness nil="true"></sureness>
                              <node-type-id type="integer">10003</node-type-id>
                              <created-at type="datetime">2013-07-25T14:21:17-04:00</created-at>
                              <updated-at type="datetime">2013-07-25T14:21:17-04:00</updated-at>
                              <pri-name>Isa</pri-name>
                              <deleted-at nil="true"></deleted-at>
                              <children type="array"/>
                            </child>
                          </children>
                        </child>
                        <child>
                          <start-date nil="true"></start-date>
                          <pub-comments>&#8220;Rendille is spoken by a group of nomadic pastoralists&#8221; (Black 1974:14).</pub-comments>
                          <geography>Northern Kenya to the east of Lake Rudolf.</geography>
                          <updater-id type="integer">10640</updater-id>
                          <id type="integer">957231</id>
                          <end-date nil="true"></end-date>
                          <creator-id type="integer">10640</creator-id>
                          <codes>rel</codes>
                          <is-default type="integer">0</is-default>
                          <created-by>emily</created-by>
                          <confidence>y</confidence>
                          <updated-by>emily</updated-by>
                          <tree-val>Lowland East Cushitic, a subtree of Afroasiatic: Black 1974</tree-val>
                          <publications>Black, Paul. 1974. Lowland East Cushitic: Subgrouping and Reconstruction. </publications>
                          <node-status-id nil="true"></node-status-id>
                          <alt-names></alt-names>
                          <node-type>Language</node-type>
                          <status nil="true"></status>
                          <other-codes></other-codes>
                          <tree-id type="integer">24398</tree-id>
                          <sureness type="integer">0</sureness>
                          <node-type-id type="integer">10001</node-type-id>
                          <created-at type="datetime">2013-07-25T14:21:18-04:00</created-at>
                          <updated-at type="datetime">2013-07-25T14:21:18-04:00</updated-at>
                          <pri-name>Rendille</pri-name>
                          <deleted-at nil="true"></deleted-at>
                          <children type="array"/>
                        </child>
                      </children>
                    </child>
                    <child>
                      <start-date nil="true"></start-date>
                      <pub-comments>&#8220;Bender (1971:218) estimates that the number of Baiso speakers as five hundred&#8221; (Black 1974:14).</pub-comments>
                      <geography>On Gidicho Island in the nortern part of Lake Abaya in southwestern Ethiopia.</geography>
                      <updater-id type="integer">10640</updater-id>
                      <id type="integer">957221</id>
                      <end-date nil="true"></end-date>
                      <creator-id type="integer">10640</creator-id>
                      <codes>bsw</codes>
                      <is-default type="integer">0</is-default>
                      <created-by>emily</created-by>
                      <confidence>y</confidence>
                      <updated-by>emily</updated-by>
                      <tree-val>Lowland East Cushitic, a subtree of Afroasiatic: Black 1974</tree-val>
                      <publications>Black, Paul. 1974. Lowland East Cushitic: Subgrouping and Reconstruction. </publications>
                      <node-status-id nil="true"></node-status-id>
                      <alt-names></alt-names>
                      <node-type>Language</node-type>
                      <status nil="true"></status>
                      <other-codes></other-codes>
                      <tree-id type="integer">24398</tree-id>
                      <sureness type="integer">0</sureness>
                      <node-type-id type="integer">10001</node-type-id>
                      <created-at type="datetime">2013-07-25T14:21:17-04:00</created-at>
                      <updated-at type="datetime">2013-07-25T14:21:17-04:00</updated-at>
                      <pri-name>Baiso</pri-name>
                      <deleted-at nil="true"></deleted-at>
                      <children type="array"/>
                    </child>
                  </children>
                </child>
                <child>
                  <start-date nil="true"></start-date>
                  <pub-comments></pub-comments>
                  <geography nil="true"></geography>
                  <updater-id type="integer">10640</updater-id>
                  <id type="integer">957232</id>
                  <end-date nil="true"></end-date>
                  <creator-id type="integer">10640</creator-id>
                  <codes>glbo</codes>
                  <is-default type="integer">0</is-default>
                  <created-by>emily</created-by>
                  <confidence>y</confidence>
                  <updated-by>emily</updated-by>
                  <tree-val>Lowland East Cushitic, a subtree of Afroasiatic: Black 1974</tree-val>
                  <publications>Black, Paul. 1974. Lowland East Cushitic: Subgrouping and Reconstruction. </publications>
                  <node-status-id nil="true"></node-status-id>
                  <alt-names></alt-names>
                  <node-type>Subgroup</node-type>
                  <status nil="true"></status>
                  <other-codes></other-codes>
                  <tree-id type="integer">24398</tree-id>
                  <sureness type="integer">0</sureness>
                  <node-type-id type="integer">10000</node-type-id>
                  <created-at type="datetime">2013-07-25T14:21:18-04:00</created-at>
                  <updated-at type="datetime">2013-07-25T14:21:18-04:00</updated-at>
                  <pri-name>Arbore-Dasenech</pri-name>
                  <deleted-at nil="true"></deleted-at>
                  <children type="array">
                    <child>
                      <start-date nil="true"></start-date>
                      <pub-comments>&#8220;It is spoken by some eighteen thousand speakers&#8221; (Black 1974:13).</pub-comments>
                      <geography>Around the northern end of Lake Rudolf, near the Intersection of the borders of Ethiopia, Kenya, and the Sudan.</geography>
                      <updater-id type="integer">10640</updater-id>
                      <id type="integer">957233</id>
                      <end-date nil="true"></end-date>
                      <creator-id type="integer">10640</creator-id>
                      <codes>dsh</codes>
                      <is-default type="integer">0</is-default>
                      <created-by>emily</created-by>
                      <confidence>y</confidence>
                      <updated-by>emily</updated-by>
                      <tree-val>Lowland East Cushitic, a subtree of Afroasiatic: Black 1974</tree-val>
                      <publications>Black, Paul. 1974. Lowland East Cushitic: Subgrouping and Reconstruction. </publications>
                      <node-status-id nil="true"></node-status-id>
                      <alt-names>Geleba, Galab, Marille, Reshiat</alt-names>
                      <node-type>Language</node-type>
                      <status nil="true"></status>
                      <other-codes></other-codes>
                      <tree-id type="integer">24398</tree-id>
                      <sureness type="integer">0</sureness>
                      <node-type-id type="integer">10001</node-type-id>
                      <created-at type="datetime">2013-07-25T14:21:18-04:00</created-at>
                      <updated-at type="datetime">2013-07-25T14:21:18-04:00</updated-at>
                      <pri-name>Dasenech</pri-name>
                      <deleted-at nil="true"></deleted-at>
                      <children type="array"/>
                    </child>
                    <child>
                      <start-date nil="true"></start-date>
                      <pub-comments></pub-comments>
                      <geography nil="true"></geography>
                      <updater-id type="integer">10640</updater-id>
                      <id type="integer">957234</id>
                      <end-date nil="true"></end-date>
                      <creator-id type="integer">10640</creator-id>
                      <codes>arel</codes>
                      <is-default type="integer">0</is-default>
                      <created-by>emily</created-by>
                      <confidence>y</confidence>
                      <updated-by>emily</updated-by>
                      <tree-val>Lowland East Cushitic, a subtree of Afroasiatic: Black 1974</tree-val>
                      <publications>Black, Paul. 1974. Lowland East Cushitic: Subgrouping and Reconstruction. </publications>
                      <node-status-id nil="true"></node-status-id>
                      <alt-names></alt-names>
                      <node-type>Subgroup</node-type>
                      <status nil="true"></status>
                      <other-codes></other-codes>
                      <tree-id type="integer">24398</tree-id>
                      <sureness type="integer">0</sureness>
                      <node-type-id type="integer">10000</node-type-id>
                      <created-at type="datetime">2013-07-25T14:21:18-04:00</created-at>
                      <updated-at type="datetime">2013-07-25T14:21:18-04:00</updated-at>
                      <pri-name>Arbore-Elmolo</pri-name>
                      <deleted-at nil="true"></deleted-at>
                      <children type="array">
                        <child>
                          <start-date nil="true"></start-date>
                          <pub-comments>&#8220;Arbore is spoken by no more than one or two thousand speakers&#8221; (Black 1974:14).</pub-comments>
                          <geography>Along the northwestern shore of Lake Stephanie.</geography>
                          <updater-id type="integer">10640</updater-id>
                          <id type="integer">957235</id>
                          <end-date nil="true"></end-date>
                          <creator-id type="integer">10640</creator-id>
                          <codes>arv</codes>
                          <is-default type="integer">0</is-default>
                          <created-by>emily</created-by>
                          <confidence>y</confidence>
                          <updated-by>emily</updated-by>
                          <tree-val>Lowland East Cushitic, a subtree of Afroasiatic: Black 1974</tree-val>
                          <publications>Black, Paul. 1974. Lowland East Cushitic: Subgrouping and Reconstruction. </publications>
                          <node-status-id nil="true"></node-status-id>
                          <alt-names></alt-names>
                          <node-type>Language</node-type>
                          <status nil="true"></status>
                          <other-codes></other-codes>
                          <tree-id type="integer">24398</tree-id>
                          <sureness type="integer">0</sureness>
                          <node-type-id type="integer">10001</node-type-id>
                          <created-at type="datetime">2013-07-25T14:21:18-04:00</created-at>
                          <updated-at type="datetime">2013-07-25T14:21:18-04:00</updated-at>
                          <pri-name>Arbore</pri-name>
                          <deleted-at nil="true"></deleted-at>
                          <children type="array"/>
                        </child>
                        <child>
                          <start-date nil="true"></start-date>
                          <pub-comments>&#8220;While the existence of the tribe has been known since first reported by Smith (1897:331), until recently it was believed that the Elmolo spoke only Samburu, a Milotic language. More recently the existence of a distinct Elmolo language has come to be recognized...which is perhaps now spoken by no more than eight of the Elmolo&#8221; (Black 1974:14).</pub-comments>
                          <geography>On the eastern shore of the southern part of Lake Rudolf and on an adjacent island.</geography>
                          <updater-id type="integer">10640</updater-id>
                          <id type="integer">957236</id>
                          <end-date nil="true"></end-date>
                          <creator-id type="integer">10640</creator-id>
                          <codes>elo</codes>
                          <is-default type="integer">0</is-default>
                          <created-by>emily</created-by>
                          <confidence>y</confidence>
                          <updated-by>emily</updated-by>
                          <tree-val>Lowland East Cushitic, a subtree of Afroasiatic: Black 1974</tree-val>
                          <publications>Black, Paul. 1974. Lowland East Cushitic: Subgrouping and Reconstruction. </publications>
                          <node-status-id nil="true"></node-status-id>
                          <alt-names></alt-names>
                          <node-type>Language</node-type>
                          <status nil="true"></status>
                          <other-codes></other-codes>
                          <tree-id type="integer">24398</tree-id>
                          <sureness type="integer">0</sureness>
                          <node-type-id type="integer">10001</node-type-id>
                          <created-at type="datetime">2013-07-25T14:21:18-04:00</created-at>
                          <updated-at type="datetime">2013-07-25T14:21:18-04:00</updated-at>
                          <pri-name>Elmolo</pri-name>
                          <deleted-at nil="true"></deleted-at>
                          <children type="array"/>
                        </child>
                      </children>
                    </child>
                  </children>
                </child>
              </children>
            </child>
            <child>
              <start-date nil="true"></start-date>
              <pub-comments>&#8220;Saho-Afar is spoken by perhaps as many as half a million speakers of two major dialects [Saho and Afar]&#8221; (Black 1974:9).</pub-comments>
              <geography nil="true"></geography>
              <updater-id type="integer">10640</updater-id>
              <id type="integer">957209</id>
              <end-date nil="true"></end-date>
              <creator-id type="integer">10640</creator-id>
              <codes>saaf</codes>
              <is-default type="integer">0</is-default>
              <created-by>emily</created-by>
              <confidence>y</confidence>
              <updated-by>emily</updated-by>
              <tree-val>Lowland East Cushitic, a subtree of Afroasiatic: Black 1974</tree-val>
              <publications>Black, Paul. 1974. Lowland East Cushitic: Subgrouping and Reconstruction. </publications>
              <node-status-id nil="true"></node-status-id>
              <alt-names></alt-names>
              <node-type>Subgroup</node-type>
              <status nil="true"></status>
              <other-codes></other-codes>
              <tree-id type="integer">24398</tree-id>
              <sureness type="integer">0</sureness>
              <node-type-id type="integer">10000</node-type-id>
              <created-at type="datetime">2013-07-25T14:21:15-04:00</created-at>
              <updated-at type="datetime">2013-07-25T14:21:15-04:00</updated-at>
              <pri-name>Saho-Afar</pri-name>
              <deleted-at nil="true"></deleted-at>
              <children type="array">
                <child>
                  <start-date nil="true"></start-date>
                  <pub-comments></pub-comments>
                  <geography nil="true"></geography>
                  <updater-id type="integer">10640</updater-id>
                  <id type="integer">957215</id>
                  <end-date nil="true"></end-date>
                  <creator-id type="integer">10640</creator-id>
                  <codes>aar</codes>
                  <is-default type="integer">0</is-default>
                  <created-by>emily</created-by>
                  <confidence>y</confidence>
                  <updated-by>emily</updated-by>
                  <tree-val>Lowland East Cushitic, a subtree of Afroasiatic: Black 1974</tree-val>
                  <publications>Black, Paul. 1974. Lowland East Cushitic: Subgrouping and Reconstruction. </publications>
                  <node-status-id nil="true"></node-status-id>
                  <alt-names>Danakil</alt-names>
                  <node-type>Language</node-type>
                  <status nil="true"></status>
                  <other-codes></other-codes>
                  <tree-id type="integer">24398</tree-id>
                  <sureness type="integer">0</sureness>
                  <node-type-id type="integer">10001</node-type-id>
                  <created-at type="datetime">2013-07-25T14:21:16-04:00</created-at>
                  <updated-at type="datetime">2013-07-25T14:21:16-04:00</updated-at>
                  <pri-name>Afar</pri-name>
                  <deleted-at nil="true"></deleted-at>
                  <children type="array">
                    <child>
                      <start-date nil="true"></start-date>
                      <pub-comments></pub-comments>
                      <geography nil="true"></geography>
                      <updater-id type="integer">10640</updater-id>
                      <id type="integer">957217</id>
                      <end-date nil="true"></end-date>
                      <creator-id type="integer">10640</creator-id>
                      <codes>aar-sou</codes>
                      <is-default type="integer">0</is-default>
                      <created-by>emily</created-by>
                      <confidence nil="true"></confidence>
                      <updated-by>emily</updated-by>
                      <tree-val>Lowland East Cushitic, a subtree of Afroasiatic: Black 1974</tree-val>
                      <publications>Black, Paul. 1974. Lowland East Cushitic: Subgrouping and Reconstruction. </publications>
                      <node-status-id nil="true"></node-status-id>
                      <alt-names></alt-names>
                      <node-type>Dialect</node-type>
                      <status nil="true"></status>
                      <other-codes></other-codes>
                      <tree-id type="integer">24398</tree-id>
                      <sureness nil="true"></sureness>
                      <node-type-id type="integer">10003</node-type-id>
                      <created-at type="datetime">2013-07-25T14:21:16-04:00</created-at>
                      <updated-at type="datetime">2013-07-25T14:21:16-04:00</updated-at>
                      <pri-name>Southern Afar</pri-name>
                      <deleted-at nil="true"></deleted-at>
                      <children type="array"/>
                    </child>
                    <child>
                      <start-date nil="true"></start-date>
                      <pub-comments></pub-comments>
                      <geography>Central Danakil</geography>
                      <updater-id type="integer">10640</updater-id>
                      <id type="integer">957218</id>
                      <end-date nil="true"></end-date>
                      <creator-id type="integer">10640</creator-id>
                      <codes>aar-aus</codes>
                      <is-default type="integer">0</is-default>
                      <created-by>emily</created-by>
                      <confidence nil="true"></confidence>
                      <updated-by>emily</updated-by>
                      <tree-val>Lowland East Cushitic, a subtree of Afroasiatic: Black 1974</tree-val>
                      <publications>Black, Paul. 1974. Lowland East Cushitic: Subgrouping and Reconstruction. </publications>
                      <node-status-id nil="true"></node-status-id>
                      <alt-names></alt-names>
                      <node-type>Dialect</node-type>
                      <status nil="true"></status>
                      <other-codes></other-codes>
                      <tree-id type="integer">24398</tree-id>
                      <sureness nil="true"></sureness>
                      <node-type-id type="integer">10003</node-type-id>
                      <created-at type="datetime">2013-07-25T14:21:16-04:00</created-at>
                      <updated-at type="datetime">2013-07-25T14:21:17-04:00</updated-at>
                      <pri-name>Aussa</pri-name>
                      <deleted-at nil="true"></deleted-at>
                      <children type="array"/>
                    </child>
                    <child>
                      <start-date nil="true"></start-date>
                      <pub-comments></pub-comments>
                      <geography nil="true"></geography>
                      <updater-id type="integer">10640</updater-id>
                      <id type="integer">957216</id>
                      <end-date nil="true"></end-date>
                      <creator-id type="integer">10640</creator-id>
                      <codes>aar-nor</codes>
                      <is-default type="integer">0</is-default>
                      <created-by>emily</created-by>
                      <confidence nil="true"></confidence>
                      <updated-by>emily</updated-by>
                      <tree-val>Lowland East Cushitic, a subtree of Afroasiatic: Black 1974</tree-val>
                      <publications>Black, Paul. 1974. Lowland East Cushitic: Subgrouping and Reconstruction. </publications>
                      <node-status-id nil="true"></node-status-id>
                      <alt-names></alt-names>
                      <node-type>Dialect</node-type>
                      <status nil="true"></status>
                      <other-codes></other-codes>
                      <tree-id type="integer">24398</tree-id>
                      <sureness nil="true"></sureness>
                      <node-type-id type="integer">10003</node-type-id>
                      <created-at type="datetime">2013-07-25T14:21:16-04:00</created-at>
                      <updated-at type="datetime">2013-07-25T14:21:16-04:00</updated-at>
                      <pri-name>Northern Afar</pri-name>
                      <deleted-at nil="true"></deleted-at>
                      <children type="array"/>
                    </child>
                  </children>
                </child>
                <child>
                  <start-date nil="true"></start-date>
                  <pub-comments>"Although Saho and Afar have often been characterized as being distinct languages, Mahaffy states that they are connected by a chain of pairs of mutually intelligible dialects" (Black: 1974 9).</pub-comments>
                  <geography>Danakil Desert in northeastern Ethiopia and the northern half of French Somaliland, and to the north of this area in the vicinity of the Red Sea Port of Massawa.</geography>
                  <updater-id type="integer">10640</updater-id>
                  <id type="integer">957210</id>
                  <end-date nil="true"></end-date>
                  <creator-id type="integer">10640</creator-id>
                  <codes>ssy</codes>
                  <is-default type="integer">0</is-default>
                  <created-by>emily</created-by>
                  <confidence>y</confidence>
                  <updated-by>emily</updated-by>
                  <tree-val>Lowland East Cushitic, a subtree of Afroasiatic: Black 1974</tree-val>
                  <publications>Black, Paul. 1974. Lowland East Cushitic: Subgrouping and Reconstruction. </publications>
                  <node-status-id nil="true"></node-status-id>
                  <alt-names></alt-names>
                  <node-type>Language</node-type>
                  <status nil="true"></status>
                  <other-codes></other-codes>
                  <tree-id type="integer">24398</tree-id>
                  <sureness type="integer">0</sureness>
                  <node-type-id type="integer">10001</node-type-id>
                  <created-at type="datetime">2013-07-25T14:21:15-04:00</created-at>
                  <updated-at type="datetime">2013-07-25T14:21:16-04:00</updated-at>
                  <pri-name>Saho</pri-name>
                  <deleted-at nil="true"></deleted-at>
                  <children type="array">
                    <child>
                      <start-date nil="true"></start-date>
                      <pub-comments></pub-comments>
                      <geography nil="true"></geography>
                      <updater-id type="integer">10640</updater-id>
                      <id type="integer">957212</id>
                      <end-date nil="true"></end-date>
                      <creator-id type="integer">10640</creator-id>
                      <codes>ssy-min</codes>
                      <is-default type="integer">0</is-default>
                      <created-by>emily</created-by>
                      <confidence nil="true"></confidence>
                      <updated-by>emily</updated-by>
                      <tree-val>Lowland East Cushitic, a subtree of Afroasiatic: Black 1974</tree-val>
                      <publications>Black, Paul. 1974. Lowland East Cushitic: Subgrouping and Reconstruction. </publications>
                      <node-status-id nil="true"></node-status-id>
                      <alt-names></alt-names>
                      <node-type>Dialect</node-type>
                      <status nil="true"></status>
                      <other-codes></other-codes>
                      <tree-id type="integer">24398</tree-id>
                      <sureness nil="true"></sureness>
                      <node-type-id type="integer">10003</node-type-id>
                      <created-at type="datetime">2013-07-25T14:21:16-04:00</created-at>
                      <updated-at type="datetime">2013-07-25T14:21:16-04:00</updated-at>
                      <pri-name>Miniferi</pri-name>
                      <deleted-at nil="true"></deleted-at>
                      <children type="array"/>
                    </child>
                    <child>
                      <start-date nil="true"></start-date>
                      <pub-comments></pub-comments>
                      <geography nil="true"></geography>
                      <updater-id type="integer">10640</updater-id>
                      <id type="integer">957213</id>
                      <end-date nil="true"></end-date>
                      <creator-id type="integer">10640</creator-id>
                      <codes>ssy-iro</codes>
                      <is-default type="integer">0</is-default>
                      <created-by>emily</created-by>
                      <confidence nil="true"></confidence>
                      <updated-by>emily</updated-by>
                      <tree-val>Lowland East Cushitic, a subtree of Afroasiatic: Black 1974</tree-val>
                      <publications>Black, Paul. 1974. Lowland East Cushitic: Subgrouping and Reconstruction. </publications>
                      <node-status-id nil="true"></node-status-id>
                      <alt-names></alt-names>
                      <node-type>Dialect</node-type>
                      <status nil="true"></status>
                      <other-codes></other-codes>
                      <tree-id type="integer">24398</tree-id>
                      <sureness nil="true"></sureness>
                      <node-type-id type="integer">10003</node-type-id>
                      <created-at type="datetime">2013-07-25T14:21:16-04:00</created-at>
                      <updated-at type="datetime">2013-07-25T14:21:16-04:00</updated-at>
                      <pri-name>Irob</pri-name>
                      <deleted-at nil="true"></deleted-at>
                      <children type="array"/>
                    </child>
                    <child>
                      <start-date nil="true"></start-date>
                      <pub-comments></pub-comments>
                      <geography nil="true"></geography>
                      <updater-id type="integer">10640</updater-id>
                      <id type="integer">957211</id>
                      <end-date nil="true"></end-date>
                      <creator-id type="integer">10640</creator-id>
                      <codes>ssy-ass</codes>
                      <is-default type="integer">0</is-default>
                      <created-by>emily</created-by>
                      <confidence nil="true"></confidence>
                      <updated-by>emily</updated-by>
                      <tree-val>Lowland East Cushitic, a subtree of Afroasiatic: Black 1974</tree-val>
                      <publications>Black, Paul. 1974. Lowland East Cushitic: Subgrouping and Reconstruction. </publications>
                      <node-status-id nil="true"></node-status-id>
                      <alt-names></alt-names>
                      <node-type>Dialect</node-type>
                      <status nil="true"></status>
                      <other-codes></other-codes>
                      <tree-id type="integer">24398</tree-id>
                      <sureness nil="true"></sureness>
                      <node-type-id type="integer">10003</node-type-id>
                      <created-at type="datetime">2013-07-25T14:21:16-04:00</created-at>
                      <updated-at type="datetime">2013-07-25T14:21:16-04:00</updated-at>
                      <pri-name>Assaorta</pri-name>
                      <deleted-at nil="true"></deleted-at>
                      <children type="array"/>
                    </child>
                    <child>
                      <start-date nil="true"></start-date>
                      <pub-comments></pub-comments>
                      <geography nil="true"></geography>
                      <updater-id type="integer">10640</updater-id>
                      <id type="integer">957214</id>
                      <end-date nil="true"></end-date>
                      <creator-id type="integer">10640</creator-id>
                      <codes>ssy-had</codes>
                      <is-default type="integer">0</is-default>
                      <created-by>emily</created-by>
                      <confidence nil="true"></confidence>
                      <updated-by>emily</updated-by>
                      <tree-val>Lowland East Cushitic, a subtree of Afroasiatic: Black 1974</tree-val>
                      <publications>Black, Paul. 1974. Lowland East Cushitic: Subgrouping and Reconstruction. </publications>
                      <node-status-id nil="true"></node-status-id>
                      <alt-names></alt-names>
                      <node-type>Dialect</node-type>
                      <status nil="true"></status>
                      <other-codes></other-codes>
                      <tree-id type="integer">24398</tree-id>
                      <sureness nil="true"></sureness>
                      <node-type-id type="integer">10003</node-type-id>
                      <created-at type="datetime">2013-07-25T14:21:16-04:00</created-at>
                      <updated-at type="datetime">2013-07-25T14:21:16-04:00</updated-at>
                      <pri-name>Hadu</pri-name>
                      <deleted-at nil="true"></deleted-at>
                      <children type="array"/>
                    </child>
                  </children>
                </child>
              </children>
            </child>
          </children>
        </child>
        <child>
          <start-date nil="true"></start-date>
          <pub-comments></pub-comments>
          <geography nil="true"></geography>
          <updater-id type="integer">10640</updater-id>
          <id type="integer">957206</id>
          <end-date nil="true"></end-date>
          <creator-id type="integer">10640</creator-id>
          <codes>hdy</codes>
          <is-default type="integer">0</is-default>
          <created-by>emily</created-by>
          <confidence>y</confidence>
          <updated-by>emily</updated-by>
          <tree-val>Lowland East Cushitic, a subtree of Afroasiatic: Black 1974</tree-val>
          <publications>Black, Paul. 1974. Lowland East Cushitic: Subgrouping and Reconstruction. </publications>
          <node-status-id nil="true"></node-status-id>
          <alt-names></alt-names>
          <node-type>Language</node-type>
          <status nil="true"></status>
          <other-codes></other-codes>
          <tree-id type="integer">24398</tree-id>
          <sureness type="integer">0</sureness>
          <node-type-id type="integer">10001</node-type-id>
          <created-at type="datetime">2013-07-25T14:21:15-04:00</created-at>
          <updated-at type="datetime">2013-07-25T14:21:15-04:00</updated-at>
          <pri-name>Hadiyya</pri-name>
          <deleted-at nil="true"></deleted-at>
          <children type="array"/>
        </child>
        <child>
          <start-date nil="true"></start-date>
          <pub-comments></pub-comments>
          <geography nil="true"></geography>
          <updater-id type="integer">10640</updater-id>
          <id type="integer">957207</id>
          <end-date nil="true"></end-date>
          <creator-id type="integer">10640</creator-id>
          <codes>gwd</codes>
          <is-default type="integer">0</is-default>
          <created-by>emily</created-by>
          <confidence>y</confidence>
          <updated-by>emily</updated-by>
          <tree-val>Lowland East Cushitic, a subtree of Afroasiatic: Black 1974</tree-val>
          <publications>Black, Paul. 1974. Lowland East Cushitic: Subgrouping and Reconstruction. </publications>
          <node-status-id nil="true"></node-status-id>
          <alt-names></alt-names>
          <node-type>Language</node-type>
          <status nil="true"></status>
          <other-codes></other-codes>
          <tree-id type="integer">24398</tree-id>
          <sureness type="integer">0</sureness>
          <node-type-id type="integer">10001</node-type-id>
          <created-at type="datetime">2013-07-25T14:21:15-04:00</created-at>
          <updated-at type="datetime">2013-07-25T14:21:15-04:00</updated-at>
          <pri-name>Gawwada</pri-name>
          <deleted-at nil="true"></deleted-at>
          <children type="array"/>
        </child>
      </children>
    </root>
    <description>Lowland East Cushitic, a subtree of Afroasiatic: Black 1974</description>
  </tree>
</hash>
